smartswitch/__init__.py
smartswitch/core.py
smartswitch/plugins/__init__.py
smartswitch/plugins/logging.py
smartswitch/plugins/pydantic.py
smartswitch-0.11.0.dist-info/licenses/LICENSE
smartswitch-0.11.0.dist-info/METADATA
smartswitch-0.11.0.dist-info/WHEEL
smartswitch-0.11.0.dist-info/top_level.txt
smartswitch-0.11.0.dist-info/RECORD
